Metadata-Version: 1.0
Name: feishu-message
Version: 1.0.0
Summary: Send Message To Feishu
Home-page: https://github.com/yinhuanyi/feishu-message
Author: Robby
Author-email: yinhuanyicn@gmail.com
License: MIT
Platform: UNKNOWN
